polarion_mcp/__init__.py
polarion_mcp/cli.py
polarion_mcp/client.py
polarion_mcp/server.py
polarion_mcp-2.0.0.dist-info/METADATA
polarion_mcp-2.0.0.dist-info/WHEEL
polarion_mcp-2.0.0.dist-info/entry_points.txt
polarion_mcp-2.0.0.dist-info/licenses/LICENSE
polarion_mcp-2.0.0.dist-info/RECORD
