Metadata-Version: 2.4
Name: polarion-mcp
Version: 2.0.0
Summary: Polarion MCP Server - Model Context Protocol integration for Siemens Polarion ALM
Project-URL: Homepage, https://github.com/Sdunga1/Polarion-MCP
Project-URL: Documentation, https://github.com/Sdunga1/Polarion-MCP/blob/main/README.md
Project-URL: Repository, https://github.com/Sdunga1/Polarion-MCP.git
Project-URL: Issues, https://github.com/Sdunga1/Polarion-MCP/issues
Author: ATOMS Team
License: MIT
License-File: LICENSE
Keywords: mcp,model-context-protocol,polarion,requirements
Classifier: Development Status :: 4 - Beta
Classifier: Intended Audience :: Developers
Classifier: License :: OSI Approved :: MIT License
Classifier: Programming Language :: Python :: 3
Classifier: Programming Language :: Python :: 3.10
Classifier: Programming Language :: Python :: 3.11
Classifier: Programming Language :: Python :: 3.12
Classifier: Topic :: Software Development :: Libraries :: Python Modules
Requires-Python: >=3.10
Requires-Dist: loguru>=0.7.0
Requires-Dist: mcp>=0.1.0
Requires-Dist: requests>=2.31.0
Requires-Dist: selenium>=4.0.0
Requires-Dist: webdriver-manager>=4.0.0
